{"total":28,"rows":[
	{"numero":"1","fabricante":"","existe":"","estado":"","modeloequipo":"","diametro":"","potencia":"","nivelrx":"","observaciones":"","idevento":""},	
	{"numero":"2","fabricante":"","existe":"","estado":"","modeloequipo":"","diametro":"","potencia":"","nivelrx":"","observaciones":"","idevento":""},	
	{"numero":"3","fabricante":"","existe":"","estado":"","modeloequipo":"","diametro":"","potencia":"","nivelrx":"","observaciones":"","idevento":""},	
	{"numero":"4","fabricante":"","existe":"","estado":"","modeloequipo":"","diametro":"","potencia":"","nivelrx":"","observaciones":"","idevento":""},	
	{"numero":"5","fabricante":"","existe":"","estado":"","modeloequipo":"","diametro":"","potencia":"","nivelrx":"","observaciones":"","idevento":""}			
]}